{"record":"conversation","schema":"imessage","schema_version":4,"chat_identifier":"chat2000000039","service":"iMessage","conversation_type":"group","group_title":"Neighborhood Watch","participants":[{"handle":"+15551100022","name_hint":"Zane Vargas"},{"handle":"+15551100013","name_hint":"Omar Moss"},{"handle":"+15551100047","name_hint":"Zoe Upton"},{"handle":"+15551100031","name_hint":"Ivy Ellis"},{"handle":"+15551100018","name_hint":"Vera Ross"},{"handle":"+15551100032","name_hint":"Jade Frost"},{"handle":"+15551100016","name_hint":"Seth Park"},{"handle":"+15551100033","name_hint":"Kyle Grant"}],"exported_at":"2026-07-14T12:00:00-04:00"}
{"guid":"grp-39-0","is_from_me":true,"record":"message","service":"SMS","text":"Zane That restaurant was amazing.","timestamp":"2016-01-01T09:00:00-04:00","timestamp_utc":"2016-01-01T13:00:00+00:00"}
{"attachments":[{"mime_type":"image/jpeg","original_name":"IMG_2847.jpg","path":"attachments/sunset.jpg"}],"guid":"grp-39-1","is_from_me":false,"record":"message","sender":"+15551100013","service":"iMessage","text":"Omar We should plan a trip this summer.","timestamp":"2017-02-02T10:01:00-04:00","timestamp_utc":"2017-02-02T14:01:00+00:00"}
{"guid":"grp-39-2","is_from_me":false,"record":"message","sender":"+15551100047","service":"iMessage","text":"Zoe Sounds good to me.","timestamp":"2018-03-03T11:02:00-04:00","timestamp_utc":"2018-03-03T15:02:00+00:00"}
{"guid":"grp-39-3","is_from_me":false,"record":"message","sender":"+15551100031","service":"iMessage","text":"Ivy Call me when you're free.","timestamp":"2019-04-04T12:03:00-04:00","timestamp_utc":"2019-04-04T16:03:00+00:00"}
{"guid":"grp-39-4","is_from_me":false,"record":"message","sender":"+15551100018","service":"iMessage","text":"Vera That restaurant was amazing.","timestamp":"2020-05-05T13:04:00-04:00","timestamp_utc":"2020-05-05T17:04:00+00:00"}
{"guid":"grp-39-5","is_from_me":false,"record":"message","sender":"+15551100032","service":"iMessage","text":"Jade Call me when you're free.","timestamp":"2021-06-06T14:05:00-04:00","timestamp_utc":"2021-06-06T18:05:00+00:00"}
{"guid":"grp-39-6","is_from_me":false,"record":"message","sender":"+15551100016","service":"iMessage","text":"Seth On my way now.","timestamp":"2022-07-07T15:06:00-04:00","timestamp_utc":"2022-07-07T19:06:00+00:00"}
{"guid":"grp-39-7","is_from_me":true,"record":"message","service":"iMessage","text":"Kyle Call me when you're free.","timestamp":"2023-08-08T16:07:00-04:00","timestamp_utc":"2023-08-08T20:07:00+00:00"}
{"guid":"grp-39-8","is_from_me":false,"record":"message","sender":"+15551100022","service":"iMessage","text":"Zane On my way now.","timestamp":"2024-09-09T17:08:00-04:00","timestamp_utc":"2024-09-09T21:08:00+00:00"}
{"attachments":[{"mime_type":"image/jpeg","original_name":"IMG_2847.jpg","path":"attachments/sunset.jpg"}],"guid":"grp-39-9","is_from_me":false,"record":"message","sender":"+15551100013","service":"iMessage","text":"Omar Running a few minutes late!","timestamp":"2025-10-10T18:09:00-04:00","timestamp_utc":"2025-10-10T22:09:00+00:00"}
{"attachments":[{"mime_type":"image/jpeg","original_name":"IMG_3102.jpg","path":"attachments/park.jpg"}],"guid":"grp-39-10","is_from_me":false,"record":"message","sender":"+15551100047","service":"iMessage","text":"Zoe Can you pick up milk on the way home?","timestamp":"2026-11-11T09:10:00-04:00","timestamp_utc":"2026-11-11T13:10:00+00:00"}
